setup.py
pytubemp3/__init__.py
pytubemp3/__main__.py
pytubemp3/captions.py
pytubemp3/cipher.py
pytubemp3/cli.py
pytubemp3/compat.py
pytubemp3/exceptions.py
pytubemp3/extract.py
pytubemp3/helpers.py
pytubemp3/itags.py
pytubemp3/logging.py
pytubemp3/mixins.py
pytubemp3/monostate.py
pytubemp3/query.py
pytubemp3/request.py
pytubemp3/streams.py
pytubemp3/version.py
pytubemp3.egg-info/PKG-INFO
pytubemp3.egg-info/SOURCES.txt
pytubemp3.egg-info/dependency_links.txt
pytubemp3.egg-info/not-zip-safe
pytubemp3.egg-info/top_level.txt