Metadata-Version: 1.0
Name: pytubemp3
Version: 0.3
Summary: downloader
Home-page: UNKNOWN
Author: abdiwoli hassen
Author-email: abdiwolih@gmail.com
License: UNKNOWN
Platform: UNKNOWN
